README.md
setup.py
hashedml/__init__.py
hashedml/hashedml.py
hashedml.egg-info/PKG-INFO
hashedml.egg-info/SOURCES.txt
hashedml.egg-info/dependency_links.txt
hashedml.egg-info/entry_points.txt
hashedml.egg-info/requires.txt
hashedml.egg-info/top_level.txt