Metadata-Version: 2.1
Name: hashedml
Version: 0.0.3
Summary: Hash based machine learning
Home-page: https://github.com/mtingers/hashedml
Author: Matth Ingersoll
Author-email: matth@mtingers.com
Maintainer: Matth Ingersoll
Maintainer-email: matth@mtingers.com
License: MIT
Download-URL: https://pypi.python.org/pypi/hashedml
Platform: UNKNOWN
Classifier: Development Status :: 1 - Planning
Classifier: Intended Audience :: Developers
Classifier: License :: OSI Approved :: MIT License
Classifier: Natural Language :: English
Classifier: Operating System :: OS Independent
Classifier: Programming Language :: Python
Classifier: Topic :: Scientific/Engineering :: Artificial Intelligence
